README.txt
setup.cfg
setup.py
mathhelp/__init__.py
mathhelp.egg-info/PKG-INFO
mathhelp.egg-info/SOURCES.txt
mathhelp.egg-info/dependency_links.txt
mathhelp.egg-info/requires.txt
mathhelp.egg-info/top_level.txt