Metadata-Version: 1.1
Name: mathhelp
Version: 0.1.9
Summary: Help for complex calculations, and homework
Home-page: https://github.com/hi101000/mathhelp
Author: Ishan Roychowdhury
Author-email: piklenews@gmail.com
License: MIT
Download-URL: https://github.com/hi101000/mathhelp/releases/tag/v.0.1.9
Keywords: Help,Math
Platform: UNKNOWN
Classifier: Development Status :: 5 - Production/Stable
Classifier: Intended Audience :: Developers
Classifier: Topic :: Software Development :: Build Tools
Classifier: License :: OSI Approved :: MIT License
Classifier: Programming Language :: Python :: 3
Classifier: Programming Language :: Python :: 3.4
Classifier: Programming Language :: Python :: 3.5
Classifier: Programming Language :: Python :: 3.6
